luanon/__init__.py
luanon/base.py
luanon/cloudscraper/__init__.py
luanon/cloudscraper/a.js
luanon/cloudscraper/cf_challenge.py
luanon/cloudscraper/cf_error.py
luanon/cloudscraper/cf_exception.py
luanon/cloudscraper/cf_main.py
luanon/cloudscraper/cf_util.py
luanon/cloudscraper/main.py
luanon/cloudscraper/setup.py
luanon/cloudscraper/assets/index.html
luanon/cloudscraper/cf_body/__init__.py
luanon/cloudscraper/cf_body/cf_base_body.py
luanon/cloudscraper/cf_body/cf_lz_string.py
luanon/cloudscraper/cf_body/cf_request_body.py
luanon/cloudscraper/cf_body/cf_response_body.py
luanon/cloudscraper/jsdom_runtime/__init__.py
luanon/cloudscraper/jsdom_runtime/jsdom_runtime.js
luanon/cloudscraper/jsdom_runtime/jsdom_runtime.py
luanon/hcaptcha/a.jpg
luanon/hcaptcha/a.py
luanon/hcaptcha/b.jpg
luanon/hcaptcha/b.py
luanon/hcaptcha/base_hcaptcha.py
luanon/hcaptcha/c.jpg
luanon/hcaptcha/c.py
luanon/hcaptcha/hcaptcha.py
luanon/hcaptcha/main.py
luanon/hcaptcha/utils_hcaptcha.py
luanon/hcaptcha/utils/__init__.py
luanon/hcaptcha/utils/exceptions.py
luanon/hcaptcha/utils/exec_runtime.js
luanon/hcaptcha/utils/exec_runtime.py
luanon/hcaptcha/utils/motion_data.py
luanon/hcaptcha/utils/pointer.py
luanon/hcaptcha/utils/utils_pointer.py
luanon/hcaptcha/utils/vector.py
luanon/hcaptcha_new/__init__.py
luanon/hcaptcha_new/hcapt_main.py
luanon/hcaptcha_new/hcapt_type.py
luanon/hcaptcha_new/setup.py
luanon/image/__init__.py
luanon/image/image.py
luanon/image/image_exceptions.py
luanon/image/image_types.py
luanon/image/image_utils.py
luanon/image/core/__init__.py
luanon/image/core/image_core.py
luanon/image/core/jpeg.py
luanon/image/core/png.py
luanon/js_runtime/__init__.py
luanon/js_runtime/exception.py
luanon/js_runtime/js_runtime.js
luanon/js_runtime/js_runtime.py
luanon/js_runtime/setup.py
luanon-1.0.1.dev0.dist-info/LICENSE
luanon-1.0.1.dev0.dist-info/METADATA
luanon-1.0.1.dev0.dist-info/WHEEL
luanon-1.0.1.dev0.dist-info/top_level.txt
luanon-1.0.1.dev0.dist-info/RECORD
