Metadata-Version: 2.1
Name: luanon
Version: 1.0.1.dev0
Summary: Simple but gold
Home-page: https://github.com/luanon404/luanon
Author: GnU
Author-email: luanon404@gmail.com
Classifier: Programming Language :: Python :: 3
Classifier: License :: OSI Approved :: GNU General Public License v3 (GPLv3)
Requires-Python: >=3.12
License-File: LICENSE
